Workbook
Name NativeTimeline_Order_Date: #N/A
Name Slicer_Category: #N/A
Name Slicer_Region: #N/A
Name Slicer_Year: #N/A

Sheet Raw_Sales_Data
A1: Order_ID | B1: Raw_Order_Date | C1: Raw_Salesperson | D1: Raw_Region | E1: Raw_Product_Code | F1: Product_Name | G1: Raw_Units_Sold | H1: Raw_Unit_Price | I1: Cost_Price | J1: Payment_Method | K1: Raw_Payment_Status
A2: ORD-10001 | B2: 2026-06-08 | C2: priya patel | D2: EAST | E2: PRD-ACC-302 | F2: Noise Cancelling Headphones | G2: 12 | H2: 12500 | I2: 8267 | J2: UPI | K2: Paid
A3: ORD-10002 | B3: 2025-11-13 | C3: neha gupta | D3: EAST | E3: PRD-ACC-301 | F3: USB-C Docking Station | G3: 13 | H3: 8500 | I3: 5143 | J3: Credit Card | K3: pending
A4: ORD-10003 | B4: 2026-05-22 | C4: pooja sharma | D4: West | E4: PRD-FUR-201 | F4: Ergonomic Desk Chair | G4: 3 | H4: 14000 | I4: 10441 | J4: COD | K4: Paid
A5: ORD-10004 | B5: 2025-03-18 | C5: VIKRAM SINGH | D5: East | E5: PRD-ACC-302 | F5: Noise Cancelling Headphones | G5: 10 | H5: ₹ 12,500 | I5: 8801 | J5: Credit Card | K5: PENDING
A6: ORD-10005 | B6: 2025-10-12 | C6: VIKRAM SINGH | D6: south | E6: PRD-FUR-202_v1 | F6: Standing Executive Desk | G6: 8 | H6: 35000 | I6: 22572 | J6: UPI | K6: PENDING
A7: ORD-10006 | B7: 24/11/2025 | C7: VIKRAM SINGH | D7: Central | E7: PRD-ELE-101 | F7: Monitor 27inch | G7: 11 | H7: 55000 | I7: 38919 | J7: COD | K7: pending
A8: ORD-10007 | B8: 2026-04-09 | C8: priya patel | D8: north | E8: PRD-ELE-105 | F8: Android Tablet 10inch | G8: 5 | H8: INR 28000 | I8: 21639 | J8: COD | K8: paid
A9: ORD-10008 | B9: 2026-06-27 | C9: Rahul Sharma | D9: Central | E9: PRD-ACC-302 | F9: Noise Cancelling Headphones | G9: 9 pcs | H9: ₹ 12,500 | I9: 9201 | J9: Net Banking | K9: Failed
A10: ORD-10009 | B10: 2025-02-17 | C10: Ananya Roy | D10: north | E10: PRD-ELE-104 | F10: Core i7 Laptop | G10: 10 | H10: 75000 | I10: 52501 | J10: Net Banking | K10: Failed
A11: ORD-10010 | B11: 2025-04-03 | C11: priya patel | D11: EAST | E11: PRD-FUR-201_v1 | F11: Ergonomic Desk Chair | G11: 4 | H11: 14000 | I11: 10260 | J11: Cash on Delivery | K11: PENDING
A12: ORD-10011 | B12: 2025.09.08 | C12: Suresh Raina | D12: North | E12: PRD-ACC-301 | F12: USB-C Docking Station | G12: 7 | H12: 8500 | I12: 6184 | J12: Credit Card | K12: paid
A13: ORD-10012 | B13: 13/03/2025 | C13: Suresh Raina | D13: Central | E13: PRD-FUR-202 | F13: Standing Executive Desk | G13: 4 | H13: ₹ 35,000 | I13: 22680 | J13: Net Banking | K13: paid
... A35: ORD-10034 | B35: 2026-05-27 | C35: VIKRAM SINGH | D35: EAST | E35: PRD-ELE-101 | F35: Monitor 27inch | G35: 4 | H35: 55000 | I35: 34871 | J35: COD | K35: pending
A36: ORD-10035 | B36: 2025-08-12 | C36: VIKRAM SINGH | E36: PRD-ACC-302_v1 | F36: Noise Cancelling Headphones | G36: 13 | H36: INR 12500 | I36: 7503 | J36: Cash on Delivery | K36: PENDING
A37: ORD-10036 | B37: 20/03/2026 | C37: Rohan Verma | D37: East | E37: PRD-ELE-102 | F37: Mechanical Keyboard | G37: 10 | H37: ₹ 4,500 | I37: 3413 | J37: UPI | K37: pending
A38: ORD-10037 | B38: 2025-01-18 | C38: neha gupta | D38: West | E38: PRD-ELE-102 | F38: Mechanical Keyboard | G38: 8 | H38: 4500 | I38: 2705 | J38: Net Banking | K38: Paid
A39: ORD-10038 | B39: 2025-01-14 | C39: Ananya Roy | D39: Central | E39: PRD-ELE-103 | F39: Wireless Mouse | G39: 17 | H39: 2500 | I39: 1511 | J39: UPI | K39: Paid
A40: ORD-10039 | B40: 2026-05-20 | C40: Suresh Raina | D40: EAST | E40: PRD-FUR-201 | F40: Ergonomic Desk Chair | G40: 18 | H40: 14000 | I40: 9343 | J40: Cash on Delivery | K40: Paid
A41: ORD-10040 | B41: 2025-02-14 | C41: Rohan Verma | D41: West | E41: PRD-ELE-102_v3 | F41: Mechanical Keyboard | G41: 19 pcs | H41: ₹ 4,500 | I41: 2999 | J41: Credit Card | K41: pending
A42: ORD-10041 | B42: 2026-03-17 | C42: Rahul Sharma | D42: East | E42: PRD-ACC-302 | F42: Noise Cancelling Headphones | G42: 6 | H42: 12500 | I42: 7656 | J42: Cash on Delivery | K42: pending
A43: ORD-10042 | B43: 13/02/2025 | C43: Amit Kumar | D43: North | E43: PRD-FUR-201 | F43: Ergonomic Desk Chair | G43: 7 | H43: INR 14000 | I43: 9033 | J43: UPI | K43: paid
A44: ORD-10043 | B44: 2025-03-17 | C44: Suresh Raina | D44: Central | E44: PRD-ACC-301 | F44: USB-C Docking Station | G44: 10 | H44: 8500 | I44: 5453 | J44: UPI | K44: pending
A45: ORD-10044 | B45: 2025.04.02 | C45: Rahul Sharma | D45: EAST | E45: PRD-ELE-104 | F45: Core i7 Laptop | G45: 16 | H45: ₹ 75,000 | I45: 56812 | J45: Net Banking | K45: PENDING
A46: ORD-10045 | B46: 2026-01-23 | C46: pooja sharma | D46: East | E46: PRD-ELE-105_v2 | F46: Android Tablet 10inch | G46: 12 | H46: 28000 | I46: 16935 | J46: Credit Card
A47: ORD-10046 | B47: 2025-03-24 | C47: Amit Kumar | D47: East | E47: PRD-ACC-301 | F47: USB-C Docking Station | G47: 15 | H47: 8500 | I47: 5585 | J47: Cash on Delivery | K47: PENDING
A48: ORD-10047 | B48: 2026-03-03 | C48: Rohan Verma | D48: East | E48: PRD-ELE-105 | F48: Android Tablet 10inch | G48: 2 | H48: 28000 | I48: 19913 | J48: Net Banking | K48: Paid
A49: ORD-10048 | B49: 03/06/2025 | C49: Rahul Sharma | D49: North | E49: PRD-ELE-105 | F49: Android Tablet 10inch | G49: 14 pcs | H49: ₹ 28,000 | I49: 20306 | J49: Net Banking | K49: pending
A50: ORD-10049 | B50: 2025-03-12 | C50: priya patel | D50: West | E50: PRD-ELE-101 | F50: Monitor 27inch | G50: 18 | H50: INR 55000 | I50: 43704 | J50: UPI | K50: Failed
A51: ORD-10040 | B51: 2025-12-18 | C51: Rahul Sharma | D51: north | E51: PRD-ELE-102_v2 | F51: Mechanical Keyboard | G51: 17 | H51: 4500 | I51: 3145 | J51: COD | K51: paid
A52: ORD-10051 | B52: 2025-09-13 | C52: neha gupta | D52: north | E52: PRD-ACC-302 | F52: Noise Cancelling Headphones | G52: 11 | H52: 12500 | I52: 8576 | J52: Cash on Delivery | K52: Paid
A53: ORD-10052 | B53: 2025-04-06 | C53: Rahul Sharma | D53: East | E53: PRD-ELE-104 | F53: Core i7 Laptop | G53: 7 | H53: ₹ 75,000 | I53: 45542 | J53: Credit Card | K53: pending
A54: ORD-10053 | B54: 2026-02-02 | C54: Rahul Sharma | D54: North | E54: PRD-ACC-302 | F54: Noise Cancelling Headphones | G54: 3 | H54: 12500 | I54: 7524 | J54: UPI | K54: Failed
A55: ORD-10054 | B55: 08/04/2025 | C55: Rahul Sharma | D55: East | E55: PRD-ELE-104 | F55: Core i7 Laptop | G55: 5 | H55: 75000 | I55: 56214 | J55: COD | K55: Paid
A56: ORD-10055 | B56: 2026.04.20 | C56: Amit Kumar | D56: north | E56: PRD-ELE-104_v2 | F56: Core i7 Laptop | G56: 13 | H56: 75000 | I56: 50799 | J56: Net Banking | K56: paid
A57: ORD-10056 | B57: 2025-09-21 | C57: Amit Kumar | D57: North | E57: PRD-ACC-301 | F57: USB-C Docking Station | G57: 3 pcs | H57: ₹ 8,500 | I57: 5667 | J57: Cash on Delivery | K57: PENDING
A58: ORD-10057 | B58: 2025-05-12 | C58: Ananya Roy | D58: Central | E58: PRD-ELE-103 | F58: Wireless Mouse | G58: 6 | H58: 2500 | I58: 1948 | J58: Net Banking | K58: Paid
... A70: ORD-10069 | B70: 2026-04-22 | C70: Amit Kumar | D70: West | E70: PRD-ELE-103 | F70: Wireless Mouse | G70: 15 | H70: 2500 | I70: 1740 | J70: COD | K70: Paid
A71: ORD-10070 | B71: 2025-01-14 | C71: Amit Kumar | E71: PRD-FUR-202_v2 | F71: Standing Executive Desk | G71: 9 | H71: INR 35000 | I71: 27966 | J71: Net Banking | K71: Failed
A72: ORD-10071 | B72: 2025-07-16 | C72: neha gupta | D72: North | E72: PRD-ELE-101 | F72: Monitor 27inch | G72: 2 | H72: 55000 | I72: 43496 | J72: Cash on Delivery | K72: Failed
A73: ORD-10072 | B73: 21/06/2026 | C73: Rohan Verma | D73: North | E73: PRD-ELE-101 | F73: Monitor 27inch | G73: 2 pcs | H73: ₹ 55,000 | I73: 43601 | J73: UPI | K73: PENDING
A74: ORD-10073 | B74: 2026-04-23 | C74: neha gupta | D74: north | E74: PRD-FUR-201 | F74: Ergonomic Desk Chair | G74: 2 | H74: 14000 | I74: 9284 | J74: Net Banking | K74: PENDING
A75: ORD-10074 | B75: 2025-01-22 | C75: Rohan Verma | D75: EAST | E75: PRD-FUR-201 | F75: Ergonomic Desk Chair | G75: 5 | H75: 14000 | I75: 9260 | J75: COD | K75: paid
A76: ORD-10075 | B76: 2026-06-08 | C76: VIKRAM SINGH | D76: Central | E76: PRD-ELE-103_v3 | F76: Wireless Mouse | G76: 18 | H76: 2500 | I76: 1590 | J76: Net Banking | K76: paid
A77: ORD-10076 | B77: 2026-06-08 | C77: Rahul Sharma | D77: North | E77: PRD-ELE-101 | F77: Monitor 27inch | G77: 9 | H77: ₹ 55,000 | I77: 41193 | J77: Net Banking | K77: paid
A78: ORD-10077 | B78: 2026.03.20 | C78: priya patel | D78: EAST | E78: PRD-ELE-102 | F78: Mechanical Keyboard | G78: 6 | H78: INR 4500 | I78: 2975 | J78: COD | K78: pending
A79: ORD-10078 | B79: 08/01/2026 | C79: Ananya Roy | D79: EAST | E79: PRD-ELE-102 | F79: Mechanical Keyboard | G79: 14 | H79: 4500 | I79: 3314 | J79: Credit Card | K79: Failed
A80: ORD-10079 | B80: 2026-08-17 | C80: Rohan Verma | D80: south | E80: PRD-ACC-301 | F80: USB-C Docking Station | G80: 7 | H80: 8500 | I80: 6109 | J80: UPI | K80: Failed
A81: ORD-10080 | B81: 2026-01-18 | C81: Suresh Raina | D81: EAST | E81: PRD-FUR-202_v3 | F81: Standing Executive Desk | G81: 1 pcs | H81: ₹ 35,000 | I81: 26990 | J81: Cash on Delivery | K81: PENDING
A82: ORD-10081 | B82: 2026-08-06 | C82: Ananya Roy | D82: North | E82: PRD-ELE-102 | F82: Mechanical Keyboard | G82: 8 | H82: 4500 | I82: 3388 | J82: Net Banking | K82: Paid
A83: ORD-10082 | B83: 2026-03-22 | C83: pooja sharma | D83: West | E83: PRD-ELE-103 | F83: Wireless Mouse | G83: 8 | H83: 2500 | I83: 1931 | J83: Credit Card | K83: PENDING
... A90: ORD-10089 | B90: 2026-06-24 | C90: priya patel | D90: EAST | E90: PRD-FUR-201 | F90: Ergonomic Desk Chair | G90: 1 | H90: 14000 | I90: 9948 | J90: COD | K90: Paid
A91: ORD-10090 | B91: 24/07/2025 | C91: pooja sharma | D91: Central | E91: PRD-ELE-105_v3 | F91: Android Tablet 10inch | G91: 5 | H91: 28000 | I91: 21936 | J91: Cash on Delivery
A92: ORD-10091 | B92: 2026-04-04 | C92: Ananya Roy | D92: south | E92: PRD-ELE-102 | F92: Mechanical Keyboard | G92: 15 | H92: INR 4500 | I92: 3099 | J92: Credit Card | K92: Failed
A93: ORD-10092 | B93: 2026-06-06 | C93: priya patel | D93: West | E93: PRD-ELE-104 | F93: Core i7 Laptop | G93: 2 | H93: ₹ 75,000 | I93: 48516 | J93: Net Banking | K93: Failed
A94: ORD-10093 | B94: 2026-03-28 | C94: VIKRAM SINGH | D94: East | E94: PRD-ELE-101 | F94: Monitor 27inch | G94: 11 | H94: 55000 | I94: 37624 | J94: Net Banking | K94: Paid
A95: ORD-10094 | B95: 2025-12-25 | C95: Rohan Verma | D95: East | E95: PRD-ACC-302 | F95: Noise Cancelling Headphones | G95: 8 | H95: 12500 | I95: 8390 | J95: Cash on Delivery | K95: paid
A96: ORD-10095 | B96: 2025-08-20 | C96: neha gupta | D96: Central | E96: PRD-FUR-202_v1 | F96: Standing Executive Desk | G96: 15 | H96: 35000 | I96: 24361 | J96: Credit Card | K96: Failed
A97: ORD-10096 | B97: 20/02/2026 | C97: VIKRAM SINGH | D97: East | E97: PRD-ELE-102 | F97: Mechanical Keyboard | G97: 3 pcs | H97: ₹ 4,500 | I97: 2794 | J97: Net Banking | K97: paid
A98: ORD-10097 | B98: 2025-07-27 | C98: Amit Kumar | D98: North | E98: PRD-ELE-104 | F98: Core i7 Laptop | G98: 16 | H98: 75000 | I98: 49011 | J98: Cash on Delivery | K98: Paid
A99: ORD-10098 | B99: 2025-12-08 | C99: Rohan Verma | D99: south | E99: PRD-FUR-202 | F99: Standing Executive Desk | G99: 15 | H99: INR 35000 | I99: 25649 | J99: COD | K99: pending
A100: ORD-10099 | B100: 2025.11.15 | C100: Suresh Raina | D100: EAST | E100: PRD-ELE-102 | F100: Mechanical Keyboard | G100: 16 | H100: 4500 | I100: 3562 | J100: Net Banking | K100: Paid
A101: ORD-10100 | B101: 2026-04-17 | C101: Suresh Raina | D101: Central | E101: PRD-ELE-102_v2 | F101: Mechanical Keyboard | G101: 17 | H101: ₹ 4,500 | I101: 3574 | J101: Net Banking | K101: Failed
A102: ORD-10101 | B102: 2025-02-17 | C102: Suresh Raina | D102: North | E102: PRD-FUR-201 | F102: Ergonomic Desk Chair | G102: 9 | H102: 14000 | I102: 10944 | J102: COD | K102: pending
A103: ORD-10102 | B103: 07/10/2025 | C103: VIKRAM SINGH | D103: North | E103: PRD-ELE-101 | F103: Monitor 27inch | G103: 19 | H103: 55000 | I103: 39279 | J103: Credit Card | K103: Failed
... A105: ORD-10104 | B105: 2025-04-19 | C105: priya patel | D105: North | E105: PRD-ELE-105 | F105: Android Tablet 10inch | G105: 3 pcs | H105: ₹ 28,000 | I105: 17810 | J105: COD | K105: Failed
A106: ORD-10105 | B106: 2025-11-19 | C106: Amit Kumar | E106: PRD-ELE-105_v2 | F106: Android Tablet 10inch | G106: -3 | H106: INR 28000 | I106: 19608 | J106: Credit Card | K106: paid
A107: ORD-10106 | B107: 2026-03-11 | C107: Suresh Raina | D107: Central | E107: PRD-ELE-103 | F107: Wireless Mouse | G107: 7 | H107: 2500 | I107: 1863 | J107: UPI | K107: Failed
A108: ORD-10107 | B108: 2026-02-24 | C108: Suresh Raina | D108: North | E108: PRD-FUR-201 | F108: Ergonomic Desk Chair | G108: 13 | H108: 14000 | I108: 10379 | J108: COD | K108: paid
A109: ORD-10108 | B109: 18/08/2026 | C109: Ananya Roy | D109: Central | E109: PRD-ELE-104 | F109: Core i7 Laptop | G109: 1 | H109: ₹ 75,000 | I109: 53904 | J109: Net Banking | K109: paid
A110: ORD-10109 | B110: 2026-03-11 | C110: Suresh Raina | D110: south | E110: PRD-ACC-301 | F110: USB-C Docking Station | G110: 14 | H110: 8500 | I110: 6335 | J110: UPI | K110: PENDING
A111: ORD-10110 | B111: 2026.08.20 | C111: Ananya Roy | D111: North | E111: PRD-ELE-101_v1 | F111: Monitor 27inch | G111: 11 | H111: 55000 | I111: 34203 | J111: Net Banking | K111: Failed
A112: ORD-10111 | B112: 2025-10-22 | C112: Ananya Roy | D112: EAST | E112: PRD-FUR-201 | F112: Ergonomic Desk Chair | G112: 3 | H112: 14000 | I112: 8562 | J112: UPI | K112: pending
A113: ORD-10112 | B113: 2025-09-26 | C113: Rohan Verma | D113: EAST | E113: PRD-ACC-301 | F113: USB-C Docking Station | G113: 6 pcs | H113: ₹ 8,500 | I113: 6734 | J113: UPI | K113: PENDING
A114: ORD-10113 | B114: 2025-07-17 | C114: neha gupta | D114: north | E114: PRD-ELE-102 | F114: Mechanical Keyboard | G114: 12 | H114: 4500 | I114: 3447 | J114: Credit Card | K114: paid
A115: ORD-10114 | B115: 21/09/2025 | C115: Ananya Roy | D115: North | E115: PRD-ELE-105 | F115: Android Tablet 10inch | G115: 15 | H115: 28000 | I115: 17914 | J115: COD | K115: PENDING
A116: ORD-10115 | B116: 2025-02-23 | C116: priya patel | D116: North | E116: PRD-ELE-101_v3 | F116: Monitor 27inch | G116: 13 | H116: 55000 | I116: 38115 | J116: COD | K116: PENDING
A117: ORD-10116 | B117: 2026-03-02 | C117: priya patel | D117: south | E117: PRD-ELE-101 | F117: Monitor 27inch | G117: 2 | H117: ₹ 55,000 | I117: 38874 | J117: Cash on Delivery | K117: paid
A118: ORD-10117 | B118: 2025-01-28 | C118: pooja sharma | D118: north | E118: PRD-ELE-101 | F118: Monitor 27inch | G118: 2 | H118: 55000 | I118: 42082 | J118: Cash on Delivery | K118: Paid
... A135: ORD-10134 | B135: 2026-07-10 | C135: neha gupta | D135: Central | E135: PRD-ACC-302 | F135: Noise Cancelling Headphones | G135: 18 | H135: 12500 | I135: 8212 | J135: Cash on Delivery | K135: Paid
A136: ORD-10135 | B136: 2025-06-01 | C136: neha gupta | D136: West | E136: PRD-ACC-301_v3 | F136: USB-C Docking Station | G136: 9 | H136: 8500 | I136: 6402 | J136: Net Banking
A137: ORD-10136 | B137: 2025-07-24 | C137: Rahul Sharma | D137: north | E137: PRD-ELE-102 | F137: Mechanical Keyboard | G137: 19 pcs | H137: ₹ 4,500 | I137: 3101 | J137: Net Banking | K137: pending
A138: ORD-10137 | B138: 2025-07-26 | C138: pooja sharma | D138: West | E138: PRD-ELE-102 | F138: Mechanical Keyboard | G138: 13 | H138: 4500 | I138: 2906 | J138: COD | K138: paid
A139: ORD-10138 | B139: 19/10/2025 | C139: Rahul Sharma | D139: East | E139: PRD-ELE-101 | F139: Monitor 27inch | G139: 11 | H139: 55000 | I139: 36566 | J139: Cash on Delivery | K139: paid
A140: ORD-10139 | B140: 2025-10-11 | C140: Suresh Raina | D140: south | E140: PRD-FUR-201 | F140: Ergonomic Desk Chair | G140: 11 | H140: 14000 | I140: 9338 | J140: COD | K140: PENDING
A141: ORD-10140 | B141: 2026-01-18 | C141: Ananya Roy | E141: PRD-FUR-201_v3 | F141: Ergonomic Desk Chair | G141: 4 | H141: ₹ 14,000 | I141: 10753 | J141: Credit Card | K141: PENDING
A142: ORD-10141 | B142: 2025-07-23 | C142: Ananya Roy | D142: south | E142: PRD-ELE-105 | F142: Android Tablet 10inch | G142: 12 | H142: 28000 | I142: 20889 | J142: Cash on Delivery | K142: Failed
A143: ORD-10142 | B143: 2026-03-30 | C143: priya patel | D143: East | E143: PRD-ELE-105 | F143: Android Tablet 10inch | G143: 19 | H143: 28000 | I143: 17842 | J143: COD | K143: PENDING
A144: ORD-10143 | B144: 2026.02.08 | C144: neha gupta | D144: East | E144: PRD-ELE-103 | F144: Wireless Mouse | G144: 12 | H144: 2500 | I144: 1906 | J144: COD | K144: PENDING
A145: ORD-10144 | B145: 18/03/2025 | C145: Rohan Verma | D145: East | E145: PRD-ELE-103 | F145: Wireless Mouse | G145: 10 pcs | H145: ₹ 2,500 | I145: 1575 | J145: Net Banking | K145: Failed
A146: ORD-10145 | B146: 2026-03-17 | C146: Suresh Raina | D146: West | E146: PRD-FUR-201_v3 | F146: Ergonomic Desk Chair | G146: 15 | H146: 14000 | I146: 11154 | J146: COD | K146: Paid
A147: ORD-10146 | B147: 2025-01-02 | C147: Rahul Sharma | D147: EAST | E147: PRD-ACC-301 | F147: USB-C Docking Station | G147: 11 | H147: 8500 | I147: 6344 | J147: Net Banking | K147: Failed
A148: ORD-10147 | B148: 2025-01-13 | C148: Rohan Verma | D148: north | E148: PRD-FUR-202 | F148: Standing Executive Desk | G148: 10 | H148: INR 35000 | I148: 22441 | J148: UPI | K148: PENDING
A149: ORD-10148 | B149: 2025-03-17 | C149: priya patel | D149: south | E149: PRD-FUR-201 | F149: Ergonomic Desk Chair | G149: 6 | H149: ₹ 14,000 | I149: 9328 | J149: UPI | K149: pending
A150: ORD-10149 | B150: 2025-05-05 | C150: Suresh Raina | D150: EAST | E150: PRD-ELE-104 | F150: Core i7 Laptop | G150: 1 | H150: 75000 | I150: 57161 | J150: Credit Card | K150: Paid
A151: ORD-10140 | B151: 15/03/2025 | C151: Rohan Verma | D151: Central | E151: PRD-ELE-101_v3 | F151: Monitor 27inch | G151: 10 | H151: 55000 | I151: 42343 | J151: Cash on Delivery | K151: Paid
A152: ORD-10151 | B152: 2025-08-12 | C152: Ananya Roy | D152: Central | E152: PRD-ACC-301 | F152: USB-C Docking Station | G152: 1 | H152: 8500 | I152: 5295 | J152: Credit Card | K152: pending
A153: ORD-10152 | B153: 2025-09-18 | C153: Rahul Sharma | D153: Central | E153: PRD-FUR-202 | F153: Standing Executive Desk | G153: 14 pcs | H153: ₹ 35,000 | I153: 25750 | J153: Credit Card | K153: paid
... A175: ORD-10174 | B175: 21/04/2025 | C175: Amit Kumar | D175: North | E175: PRD-FUR-201 | F175: Ergonomic Desk Chair | G175: 14 | H175: 14000 | I175: 10906 | J175: UPI | K175: pending
A176: ORD-10175 | B176: 2026-05-16 | C176: neha gupta | E176: PRD-ACC-302_v3 | F176: Noise Cancelling Headphones | G176: 7 | H176: INR 12500 | I176: 8401 | J176: Cash on Delivery | K176: pending
...

Sheet Raw_Product_Catalog
A1: Product_Code | B1: Product_Name | C1: Category | D1: Standard_Price
A2: PRD-ELE-101 | B2: Monitor 27inch | C2: Electronics | D2: 55000
A3: PRD-ELE-102 | B3: Mechanical Keyboard | C3: Electronics | D3: 4500
A4: PRD-ELE-103 | B4: Wireless Mouse | C4: Electronics | D4: 2500
A5: PRD-FUR-201 | B5: Ergonomic Desk Chair | C5: Furniture | D5: 14000
A6: PRD-FUR-202 | B6: Standing Executive Desk | C6: accessories | D6: 35000
A7: PRD-ACC-301 | B7: USB-C Docking Station | C7: Accessories | D7: 8500
A8: PRD-ELE-104 | B8: Core i7 Laptop | C8: Electronics | D8: 75000
A9: PRD-ACC-302 | B9: Noise Cancelling Headphones | C9: Accessories | D9: 12500
A10: PRD-ELE-105 | B10: Android Tablet 10inch | C10: Electronics | D10: 28000

Sheet Clean_Sales_Data
A1: Order_ID | B1: Order_Date | C1: Salesperson | D1: Region | E1: Product_Code | F1: Product_Name | G1: Units_Sold | H1: Unit_Price | I1: Cost_Price | J1: Payment_Method | K1: Payment_Status | L1: Total_Sales | M1: Total_Cost | N1: Profit | O1: Profit_Margin% | P1: Category | Q1: Year | R1: Month | S1: Month_Year
A2: ORD-10001 | B2: 46181 | C2: Priya Patel | D2: East | E2: PRD-ACC-302 | F2: Noise Cancelling Headphones | G2: 12 | H2: 12500 | I2: 8267 | J2: UPI | K2: Paid | L2: =SUM(Clean_Data[[#This Row],[Units_Sold]]*Clean_Data[[#This Row],[Unit_Price]]) -> 150000 | M2: =Clean_Data[[#This Row],[Units_Sold]]*Clean_Data[[#This Row],[Cost_Price]] -> 99204 | N2: =Clean_Data[[#This Row],[Total_Sales]]-Clean_Data[[#This Row],[Total_Cost]] -> 50796 | O2: =Clean_Data[[#This Row],[Profit]]/Clean_Data[[#This Row],[Total_Sales]] -> 0.33864 | P2: =_xlfn.XLOOKUP(Clean_Data[[#This Row],[Product_Code]],Product_Catalog!A:A,Product_Catalog!C:C) -> Accessories | Q2: =IF(Clean_Data[[#This Row],[Order_Date]]="","",YEAR(Clean_Data[[#This Row],[Order_Date]])) -> 2026 | R2: =TEXT(Clean_Data[[#This Row],[Order_Date]],"mmm") -> Jun | S2: =TEXT(Clean_Data[[#This Row],[Order_Date]],"mmm-yy") -> Jun-26
A3: ORD-10002 | B3: 45974 | C3: Neha Gupta | D3: East | E3: PRD-ACC-301 | F3: USB-C Docking Station | G3: 13 | H3: 8500 | I3: 5143 | J3: Credit Card | K3: Pending | L3: =SUM(Clean_Data[[#This Row],[Units_Sold]]*Clean_Data[[#This Row],[Unit_Price]]) -> 110500 | M3: =Clean_Data[[#This Row],[Units_Sold]]*Clean_Data[[#This Row],[Cost_Price]] -> 66859 | N3: =Clean_Data[[#This Row],[Total_Sales]]-Clean_Data[[#This Row],[Total_Cost]] -> 43641 | O3: =Clean_Data[[#This Row],[Profit]]/Clean_Data[[#This Row],[Total_Sales]] -> 0.39494118 | P3: =_xlfn.XLOOKUP(Clean_Data[[#This Row],[Product_Code]],Product_Catalog!A:A,Product_Catalog!C:C) -> Accessories | Q3: =IF(Clean_Data[[#This Row],[Order_Date]]="","",YEAR(Clean_Data[[#This Row],[Order_Date]])) -> 2025 | R3: =TEXT(Clean_Data[[#This Row],[Order_Date]],"mmm") -> Nov | S3: =TEXT(Clean_Data[[#This Row],[Order_Date]],"mmm-yy") -> Nov-25
A4: ORD-10003 | B4: 46164 | C4: Pooja Sharma | D4: West | E4: PRD-FUR-201 | F4: Ergonomic Desk Chair | G4: 3 | H4: 14000 | I4: 10441 | J4: Cash on Delivery | K4: Paid | L4: =SUM(Clean_Data[[#This Row],[Units_Sold]]*Clean_Data[[#This Row],[Unit_Price]]) -> 42000 | M4: =Clean_Data[[#This Row],[Units_Sold]]*Clean_Data[[#This Row],[Cost_Price]] -> 31323 | N4: =Clean_Data[[#This Row],[Total_Sales]]-Clean_Data[[#This Row],[Total_Cost]] -> 10677 | O4: =Clean_Data[[#This Row],[Profit]]/Clean_Data[[#This Row],[Total_Sales]] -> 0.25421429 | P4: =_xlfn.XLOOKUP(Clean_Data[[#This Row],[Product_Code]],Product_Catalog!A:A,Product_Catalog!C:C) -> Furniture | Q4: =IF(Clean_Data[[#This Row],[Order_Date]]="","",YEAR(Clean_Data[[#This Row],[Order_Date]])) -> 2026 | R4: =TEXT(Clean_Data[[#This Row],[Order_Date]],"mmm") -> May | S4: =TEXT(Clean_Data[[#This Row],[Order_Date]],"mmm-yy") -> May-26
A5: ORD-10004 | B5: 45734 | C5: Vikram Singh | D5: East | E5: PRD-ACC-302 | F5: Noise Cancelling Headphones | G5: 10 | H5: 12500 | I5: 8801 | J5: Credit Card | K5: Pending | L5: =SUM(Clean_Data[[#This Row],[Units_Sold]]*Clean_Data[[#This Row],[Unit_Price]]) -> 125000 | M5: =Clean_Data[[#This Row],[Units_Sold]]*Clean_Data[[#This Row],[Cost_Price]] -> 88010 | N5: =Clean_Data[[#This Row],[Total_Sales]]-Clean_Data[[#This Row],[Total_Cost]] -> 36990 | O5: =Clean_Data[[#This Row],[Profit]]/Clean_Data[[#This Row],[Total_Sales]] -> 0.29592 | P5: =_xlfn.XLOOKUP(Clean_Data[[#This Row],[Product_Code]],Product_Catalog!A:A,Product_Catalog!C:C) -> Accessories | Q5: =IF(Clean_Data[[#This Row],[Order_Date]]="","",YEAR(Clean_Data[[#This Row],[Order_Date]])) -> 2025 | R5: =TEXT(Clean_Data[[#This Row],[Order_Date]],"mmm") -> Mar | S5: =TEXT(Clean_Data[[#This Row],[Order_Date]],"mmm-yy") -> Mar-25
A6: ORD-10005 | B6: 45942 | C6: Vikram Singh | D6: South | E6: PRD-FUR-202 | F6: Standing Executive Desk | G6: 8 | H6: 35000 | I6: 22572 | J6: UPI | K6: Pending | L6: =SUM(Clean_Data[[#This Row],[Units_Sold]]*Clean_Data[[#This Row],[Unit_Price]]) -> 280000 | M6: =Clean_Data[[#This Row],[Units_Sold]]*Clean_Data[[#This Row],[Cost_Price]] -> 180576 | N6: =Clean_Data[[#This Row],[Total_Sales]]-Clean_Data[[#This Row],[Total_Cost]] -> 99424 | O6: =Clean_Data[[#This Row],[Profit]]/Clean_Data[[#This Row],[Total_Sales]] -> 0.35508571 | P6: =_xlfn.XLOOKUP(Clean_Data[[#This Row],[Product_Code]],Product_Catalog!A:A,Product_Catalog!C:C) -> Furniture | Q6: =IF(Clean_Data[[#This Row],[Order_Date]]="","",YEAR(Clean_Data[[#This Row],[Order_Date]])) -> 2025 | R6: =TEXT(Clean_Data[[#This Row],[Order_Date]],"mmm") -> Oct | S6: =TEXT(Clean_Data[[#This Row],[Order_Date]],"mmm-yy") -> Oct-25
A7: ORD-10006 | B7: 45985 | C7: Vikram Singh | D7: Central | E7: PRD-ELE-101 | F7: Monitor 27inch | G7: 11 | H7: 55000 | I7: 38919 | J7: Cash on Delivery | K7: Pending | L7: =SUM(Clean_Data[[#This Row],[Units_Sold]]*Clean_Data[[#This Row],[Unit_Price]]) -> 605000 | M7: =Clean_Data[[#This Row],[Units_Sold]]*Clean_Data[[#This Row],[Cost_Price]] -> 428109 | N7: =Clean_Data[[#This Row],[Total_Sales]]-Clean_Data[[#This Row],[Total_Cost]] -> 176891 | O7: =Clean_Data[[#This Row],[Profit]]/Clean_Data[[#This Row],[Total_Sales]] -> 0.29238182 | P7: =_xlfn.XLOOKUP(Clean_Data[[#This Row],[Product_Code]],Product_Catalog!A:A,Product_Catalog!C:C) -> Electronics | Q7: =IF(Clean_Data[[#This Row],[Order_Date]]="","",YEAR(Clean_Data[[#This Row],[Order_Date]])) -> 2025 | R7: =TEXT(Clean_Data[[#This Row],[Order_Date]],"mmm") -> Nov | S7: =TEXT(Clean_Data[[#This Row],[Order_Date]],"mmm-yy") -> Nov-25
A8: ORD-10007 | B8: 46121 | C8: Priya Patel | D8: North | E8: PRD-ELE-105 | F8: Android Tablet 10inch | G8: 5 | H8: 28000 | I8: 21639 | J8: Cash on Delivery | K8: Paid | L8: =SUM(Clean_Data[[#This Row],[Units_Sold]]*Clean_Data[[#This Row],[Unit_Price]]) -> 140000 | M8: =Clean_Data[[#This Row],[Units_Sold]]*Clean_Data[[#This Row],[Cost_Price]] -> 108195 | N8: =Clean_Data[[#This Row],[Total_Sales]]-Clean_Data[[#This Row],[Total_Cost]] -> 31805 | O8: =Clean_Data[[#This Row],[Profit]]/Clean_Data[[#This Row],[Total_Sales]] -> 0.22717857 | P8: =_xlfn.XLOOKUP(Clean_Data[[#This Row],[Product_Code]],Product_Catalog!A:A,Product_Catalog!C:C) -> Electronics | Q8: =IF(Clean_Data[[#This Row],[Order_Date]]="","",YEAR(Clean_Data[[#This Row],[Order_Date]])) -> 2026 | R8: =TEXT(Clean_Data[[#This Row],[Order_Date]],"mmm") -> Apr | S8: =TEXT(Clean_Data[[#This Row],[Order_Date]],"mmm-yy") -> Apr-26
A9: ORD-10008 | B9: 46200 | C9: Rahul Sharma | D9: Central | E9: PRD-ACC-302 | F9: Noise Cancelling Headphones | G9: 9 | H9: 12500 | I9: 9201 | J9: Net Banking | K9: Failed | L9: =SUM(Clean_Data[[#This Row],[Units_Sold]]*Clean_Data[[#This Row],[Unit_Price]]) -> 112500 | M9: =Clean_Data[[#This Row],[Units_Sold]]*Clean_Data[[#This Row],[Cost_Price]] -> 82809 | N9: =Clean_Data[[#This Row],[Total_Sales]]-Clean_Data[[#This Row],[Total_Cost]] -> 29691 | O9: =Clean_Data[[#This Row],[Profit]]/Clean_Data[[#This Row],[Total_Sales]] -> 0.26392 | P9: =_xlfn.XLOOKUP(Clean_Data[[#This Row],[Product_Code]],Product_Catalog!A:A,Product_Catalog!C:C) -> Accessories | Q9: =IF(Clean_Data[[#This Row],[Order_Date]]="","",YEAR(Clean_Data[[#This Row],[Order_Date]])) -> 2026 | R9: =TEXT(Clean_Data[[#This Row],[Order_Date]],"mmm") -> Jun | S9: =TEXT(Clean_Data[[#This Row],[Order_Date]],"mmm-yy") -> Jun-26
A10: ORD-10009 | B10: 45705 | C10: Ananya Roy | D10: North | E10: PRD-ELE-104 | F10: Core i7 Laptop | G10: 10 | H10: 75000 | I10: 52501 | J10: Net Banking | K10: Failed | L10: =SUM(Clean_Data[[#This Row],[Units_Sold]]*Clean_Data[[#This Row],[Unit_Price]]) -> 750000 | M10: =Clean_Data[[#This Row],[Units_Sold]]*Clean_Data[[#This Row],[Cost_Price]] -> 525010 | N10: =Clean_Data[[#This Row],[Total_Sales]]-Clean_Data[[#This Row],[Total_Cost]] -> 224990 | O10: =Clean_Data[[#This Row],[Profit]]/Clean_Data[[#This Row],[Total_Sales]] -> 0.29998667 | P10: =_xlfn.XLOOKUP(Clean_Data[[#This Row],[Product_Code]],Product_Catalog!A:A,Product_Catalog!C:C) -> Electronics | Q10: =IF(Clean_Data[[#This Row],[Order_Date]]="","",YEAR(Clean_Data[[#This Row],[Order_Date]])) -> 2025 | R10: =TEXT(Clean_Data[[#This Row],[Order_Date]],"mmm") -> Feb | S10: =TEXT(Clean_Data[[#This Row],[Order_Date]],"mmm-yy") -> Feb-25
A11: ORD-10010 | B11: 45750 | C11: Priya Patel | D11: East | E11: PRD-FUR-201 | F11: Ergonomic Desk Chair | G11: 4 | H11: 14000 | I11: 10260 | J11: Cash on Delivery | K11: Pending | L11: =SUM(Clean_Data[[#This Row],[Units_Sold]]*Clean_Data[[#This Row],[Unit_Price]]) -> 56000 | M11: =Clean_Data[[#This Row],[Units_Sold]]*Clean_Data[[#This Row],[Cost_Price]] -> 41040 | N11: =Clean_Data[[#This Row],[Total_Sales]]-Clean_Data[[#This Row],[Total_Cost]] -> 14960 | O11: =Clean_Data[[#This Row],[Profit]]/Clean_Data[[#This Row],[Total_Sales]] -> 0.26714286 | P11: =_xlfn.XLOOKUP(Clean_Data[[#This Row],[Product_Code]],Product_Catalog!A:A,Product_Catalog!C:C) -> Furniture | Q11: =IF(Clean_Data[[#This Row],[Order_Date]]="","",YEAR(Clean_Data[[#This Row],[Order_Date]])) -> 2025 | R11: =TEXT(Clean_Data[[#This Row],[Order_Date]],"mmm") -> Apr | S11: =TEXT(Clean_Data[[#This Row],[Order_Date]],"mmm-yy") -> Apr-25
A12: ORD-10011 | B12: 45908 | C12: Suresh Raina | D12: North | E12: PRD-ACC-301 | F12: USB-C Docking Station | G12: 7 | H12: 8500 | I12: 6184 | J12: Credit Card | K12: Paid | L12: =SUM(Clean_Data[[#This Row],[Units_Sold]]*Clean_Data[[#This Row],[Unit_Price]]) -> 59500 | M12: =Clean_Data[[#This Row],[Units_Sold]]*Clean_Data[[#This Row],[Cost_Price]] -> 43288 | N12: =Clean_Data[[#This Row],[Total_Sales]]-Clean_Data[[#This Row],[Total_Cost]] -> 16212 | O12: =Clean_Data[[#This Row],[Profit]]/Clean_Data[[#This Row],[Total_Sales]] -> 0.27247059 | P12: =_xlfn.XLOOKUP(Clean_Data[[#This Row],[Product_Code]],Product_Catalog!A:A,Product_Catalog!C:C) -> Accessories | Q12: =IF(Clean_Data[[#This Row],[Order_Date]]="","",YEAR(Clean_Data[[#This Row],[Order_Date]])) -> 2025 | R12: =TEXT(Clean_Data[[#This Row],[Order_Date]],"mmm") -> Sep | S12: =TEXT(Clean_Data[[#This Row],[Order_Date]],"mmm-yy") -> Sep-25
A13: ORD-10012 | B13: 45729 | C13: Suresh Raina | D13: Central | E13: PRD-FUR-202 | F13: Standing Executive Desk | G13: 4 | H13: 35000 | I13: 22680 | J13: Net Banking | K13: Paid | L13: =SUM(Clean_Data[[#This Row],[Units_Sold]]*Clean_Data[[#This Row],[Unit_Price]]) -> 140000 | M13: =Clean_Data[[#This Row],[Units_Sold]]*Clean_Data[[#This Row],[Cost_Price]] -> 90720 | N13: =Clean_Data[[#This Row],[Total_Sales]]-Clean_Data[[#This Row],[Total_Cost]] -> 49280 | O13: =Clean_Data[[#This Row],[Profit]]/Clean_Data[[#This Row],[Total_Sales]] -> 0.352 | P13: =_xlfn.XLOOKUP(Clean_Data[[#This Row],[Product_Code]],Product_Catalog!A:A,Product_Catalog!C:C) -> Furniture | Q13: =IF(Clean_Data[[#This Row],[Order_Date]]="","",YEAR(Clean_Data[[#This Row],[Order_Date]])) -> 2025 | R13: =TEXT(Clean_Data[[#This Row],[Order_Date]],"mmm") -> Mar | S13: =TEXT(Clean_Data[[#This Row],[Order_Date]],"mmm-yy") -> Mar-25
... A1157: ORD-11200 | B1157: 46179 | C1157: Neha Gupta | D1157: East | E1157: PRD-ACC-301 | F1157: USB-C Docking Station | G1157: 18 | H1157: 8500 | I1157: 5184 | J1157: Cash on Delivery | K1157: Pending | L1157: =SUM(Clean_Data[[#This Row],[Units_Sold]]*Clean_Data[[#This Row],[Unit_Price]]) -> 153000 | M1157: =Clean_Data[[#This Row],[Units_Sold]]*Clean_Data[[#This Row],[Cost_Price]] -> 93312 | N1157: =Clean_Data[[#This Row],[Total_Sales]]-Clean_Data[[#This Row],[Total_Cost]] -> 59688 | O1157: =Clean_Data[[#This Row],[Profit]]/Clean_Data[[#This Row],[Total_Sales]] -> 0.39011765 | P1157: =_xlfn.XLOOKUP(Clean_Data[[#This Row],[Product_Code]],Product_Catalog!A:A,Product_Catalog!C:C) -> Accessories | Q1157: =IF(Clean_Data[[#This Row],[Order_Date]]="","",YEAR(Clean_Data[[#This Row],[Order_Date]])) -> 2026 | R1157: =TEXT(Clean_Data[[#This Row],[Order_Date]],"mmm") -> Jun | S1157: =TEXT(Clean_Data[[#This Row],[Order_Date]],"mmm-yy") -> Jun-26

Sheet Product_Catalog
A1: Product_Code | B1: Product_Name | C1: Category | D1: Standard_Price
A2: PRD-ELE-101 | B2: Monitor 27inch | C2: Electronics | D2: 55000
A3: PRD-ELE-102 | B3: Mechanical Keyboard | C3: Electronics | D3: 4500
A4: PRD-ELE-103 | B4: Wireless Mouse | C4: Electronics | D4: 2500
A5: PRD-FUR-201 | B5: Ergonomic Desk Chair | C5: Furniture | D5: 14000
A6: PRD-FUR-202 | B6: Standing Executive Desk | C6: Furniture | D6: 35000
A7: PRD-ACC-301 | B7: USB-C Docking Station | C7: Accessories | D7: 8500
A8: PRD-ELE-104 | B8: Core i7 Laptop | C8: Electronics | D8: 75000
A9: PRD-ACC-302 | B9: Noise Cancelling Headphones | C9: Accessories | D9: 12500
A10: PRD-ELE-105 | B10: Android Tablet 10inch | C10: Electronics | D10: 28000

Sheet Pivot_Table
A3: Sum of Total_Sales | C3: Sum of Profit | E3: Profit Margin% | H3: Count of Order_ID | J3: Sum of Units_Sold
A4: 309130000 | C4: 93490092 | E4: =GETPIVOTDATA("Profit",$C$3)/GETPIVOTDATA("Total_Sales",$A$3) -> 0.3024297 | H4: 1156 | J4: 11674
A7: Row Labels | B7: Sum of Total_Sales | C7: Sum of Profit | E7: Row Labels | F7: Sum of Total_Sales | H7: Row Labels | I7: Sum of Total_Sales | K7: Row Labels | L7: Sum of Total_Sales
A8: Jan | B8: 25461000 | C8: 7684360 | E8: Central | F8: 40942000 | H8: Amit Kumar | I8: 36687500 | K8: Accessories | L8: 26563500
A9: Feb | B9: 33121000 | C9: 10044059 | E9: East | F9: 89135000 | H9: Ananya Roy | I9: 33976500 | K9: Furniture | L9: 60263000
A10: Mar | B10: 34840500 | C10: 10554067 | E10: North | F10: 87296500 | H10: Rahul Sharma | I10: 39354000 | K10: Electronics | L10: 222303500
A11: Apr | B11: 32150500 | C11: 9343954 | E11: South | F11: 50492000 | H11: Rohan Verma | I11: 40264500 | K11: Grand Total | L11: 309130000
A12: May | B12: 23887000 | C12: 7200164 | E12: West | F12: 41264500 | H12: Suresh Raina | I12: 41534000
A13: Jun | B13: 30089500 | C13: 8948596 | E13: Grand Total | F13: 309130000 | H13: Grand Total | I13: 191816500
A14: Jul | B14: 33419000 | C14: 10431069
A15: Aug | B15: 25702000 | C15: 7820052
A16: Sep | B16: 18710000 | C16: 5726915
A17: Oct | B17: 21834000 | C17: 6790574
A18: Nov | B18: 15661500 | C18: 4872101
A19: Dec | B19: 14254000 | C19: 4074181
A20: Grand Total | B20: 309130000 | C20: 93490092

Sheet Dashboard
